bio2bel_kegg/__init__.py
bio2bel_kegg/__main__.py
bio2bel_kegg/cli.py
bio2bel_kegg/client.py
bio2bel_kegg/constants.py
bio2bel_kegg/manager.py
bio2bel_kegg/models.py
bio2bel_kegg/parsers.py
bio2bel_kegg/web.py
bio2bel_kegg-0.3.0.dist-info/LICENSE
bio2bel_kegg-0.3.0.dist-info/METADATA
bio2bel_kegg-0.3.0.dist-info/WHEEL
bio2bel_kegg-0.3.0.dist-info/entry_points.txt
bio2bel_kegg-0.3.0.dist-info/top_level.txt
bio2bel_kegg-0.3.0.dist-info/RECORD
